conll_iterator/ConllIterator.py
conll_iterator/Extractor.py
conll_iterator/__init__.py
conll_iterator-0.0.1.dist-info/LICENSE
conll_iterator-0.0.1.dist-info/METADATA
conll_iterator-0.0.1.dist-info/WHEEL
conll_iterator-0.0.1.dist-info/top_level.txt
conll_iterator-0.0.1.dist-info/RECORD
