Metadata-Version: 2.1
Name: conll-iterator
Version: 0.0.1
Summary: A simple iterator that reads conll files.
Home-page: https://github.com/nicolaCirillo/conll_iterator
Author: Nicola Cirillo
Author-email: Nicola Cirillo <nicola.cirillo96@outlook.it>
License: MIT
Project-URL: Homepage, https://github.com/nicolaCirillo/conll_iterator
Classifier: Programming Language :: Python :: 3
Classifier: License :: OSI Approved :: MIT License
Classifier: Operating System :: OS Independent
Requires-Python: >=3.7
License-File: LICENSE
